Metadata-Version: 2.1
Name: soda-core-trino
Version: 3.5.6
License-File: LICENSE
Requires-Dist: soda-core==3.5.6
Requires-Dist: trino>=0.315.0
